quick_processor/__init__.py
quick_processor/main.py
quick_processor-0.3.dist-info/METADATA
quick_processor-0.3.dist-info/WHEEL
quick_processor-0.3.dist-info/top_level.txt
quick_processor-0.3.dist-info/RECORD
